anac/__init__.py
anac/core/api.py
anac/core/endpoint.py
anac/core/exceptions.py
anac-0.1.2.dist-info/LICENSE
anac-0.1.2.dist-info/WHEEL
anac-0.1.2.dist-info/METADATA
anac-0.1.2.dist-info/RECORD
