Metadata-Version: 2.1
Name: anac
Version: 0.1.2
Summary: Async NetBox API Client
Home-page: https://github.com/timeforplanb123/anac
License: Apache-2.0
Keywords: netbox,api
Author: Pavel Shemetov
Author-email: pshemetov123@gmail.com
Requires-Python: >=3.8,<4.0
Classifier: License :: OSI Approved :: Apache Software License
Classifier: Programming Language :: Python :: 3
Classifier: Programming Language :: Python :: 3.10
Classifier: Programming Language :: Python :: 3.8
Classifier: Programming Language :: Python :: 3.9
Requires-Dist: httpx (>=0.22.0,<0.23.0)
Requires-Dist: pydantic (>=1.9.0,<2.0.0)
Project-URL: Documentation, https://timeforplanb123.github.io/anac/
Project-URL: Repository, https://github.com/timeforplanb123/anac
